fitting_image/__init__.py
fitting_image-0.2.dist-info/METADATA
fitting_image-0.2.dist-info/WHEEL
fitting_image-0.2.dist-info/top_level.txt
fitting_image-0.2.dist-info/RECORD
