Metadata-Version: 2.1
Name: fitting-image
Version: 0.2
Summary: Image resizing package
Author: Jolomi
Keywords: image resize PIL
Requires-Dist: Pillow
